Multi_Layer_NN/NeuralNetwork.py
Multi_Layer_NN/__init__.py
Multi_Layer_NN_Package-0.1.2.dist-info/METADATA
Multi_Layer_NN_Package-0.1.2.dist-info/WHEEL
Multi_Layer_NN_Package-0.1.2.dist-info/top_level.txt
Multi_Layer_NN_Package-0.1.2.dist-info/RECORD
