Metadata-Version: 2.1
Name: Multi-Layer-NN-Package
Version: 0.1.2
Summary: A Multy Layer Neural Network Class
Home-page: UNKNOWN
Author: Andreas Probst
Author-email: andreaspadprobst@gmail.com
License: UNKNOWN
Platform: UNKNOWN
Requires-Dist: matplotlib (>=2.2.5)
Requires-Dist: numpy (>=1.16.6)
